keystone_json_assignment/__init__.py
keystone_json_assignment/json.py
keystone_json_assignment-0.0.4.dist-info/METADATA
keystone_json_assignment-0.0.4.dist-info/RECORD
keystone_json_assignment-0.0.4.dist-info/WHEEL
keystone_json_assignment-0.0.4.dist-info/entry_points.txt
keystone_json_assignment-0.0.4.dist-info/top_level.txt
