Metadata-Version: 2.1
Name: keystone-json-assignment
Version: 0.0.4
Summary: JSON Backend for the Keystone Assignment Driver
Home-page: https://github.com/SUSE-Cloud/keystone-json-assignment
Author: Colleen Murphy
Author-email: colleen.murphy@suse.com
License: Apache-2.0
Platform: UNKNOWN
